kipu/README.md
kipu/__init__.py
kipu/auth.py
kipu/base_client.py
kipu/cli.py
kipu/client.py
kipu/examples.py
kipu/exceptions.py
kipu/flattener.py
kipu/py.typed
kipu_python-1.0.0.dist-info/licenses/LICENSE
kipu_python-1.0.0.dist-info/METADATA
kipu_python-1.0.0.dist-info/WHEEL
kipu_python-1.0.0.dist-info/entry_points.txt
kipu_python-1.0.0.dist-info/top_level.txt
kipu_python-1.0.0.dist-info/RECORD
