Metadata-Version: 2.4
Name: kipu-python
Version: 1.0.0
Summary: A comprehensive Python library for the Kipu Healthcare API with HMAC SHA1 authentication and recursive JSON flattening
Home-page: https://github.com/Rahulkumar010/kipu-python
Author: Rahul
Author-email: Rahul <rahul01110100@gmail.com>
Maintainer-email: Rahul <rahul01110100@gmail.com>
License: MIT
Project-URL: Homepage, https://github.com/Rahulkumar010/kipu-python
Project-URL: Documentation, https://kipu-python.readthedocs.io/
Project-URL: Repository, https://github.com/Rahulkumar010/kipu-python.git
Project-URL: Issues, https://github.com/Rahulkumar010/kipu-python/issues
Keywords: kipu,healthcare,api,library,medical,ehr,electronic-health-records,hmac,authentication,async,pandas,recursive-json-flattening
Classifier: Development Status :: 5 - Production/Stable
Classifier: Intended Audience :: Healthcare Industry
Classifier: Intended Audience :: Developers
Classifier: Topic :: Software Development :: Libraries :: Python Modules
Classifier: Topic :: Scientific/Engineering :: Medical Science Apps.
Classifier: License :: OSI Approved :: MIT License
Classifier: Programming Language :: Python :: 3
Classifier: Programming Language :: Python :: 3.8
Classifier: Programming Language :: Python :: 3.9
Classifier: Programming Language :: Python :: 3.10
Classifier: Programming Language :: Python :: 3.11
Classifier: Programming Language :: Python :: 3.12
Classifier: Operating System :: OS Independent
Requires-Python: >=3.8
License-File: LICENSE
Requires-Dist: aiohttp>=3.8.0
Requires-Dist: pandas>=1.3.0
Requires-Dist: numpy>=1.20.0
Requires-Dist: tqdm>=4.60.0
Provides-Extra: dev
Requires-Dist: pytest>=6.0; extra == "dev"
Requires-Dist: pytest-cov; extra == "dev"
Requires-Dist: pytest-asyncio>=0.18.0; extra == "dev"
Requires-Dist: black>=22.0.0; extra == "dev"
Requires-Dist: isort>=5.10.0; extra == "dev"
Requires-Dist: flake8>=4.0.0; extra == "dev"
Requires-Dist: mypy>=0.950; extra == "dev"
Requires-Dist: pre-commit>=2.15.0; extra == "dev"
Provides-Extra: docs
Requires-Dist: sphinx>=4.0.0; extra == "docs"
Requires-Dist: sphinx-rtd-theme>=1.0.0; extra == "docs"
Requires-Dist: sphinx-autodoc-typehints>=1.12.0; extra == "docs"
Dynamic: author
Dynamic: home-page
Dynamic: license-file
Dynamic: requires-python
